{
    "type": "FeatureCollection",
    "features": [
        {
            "type": "Feature",
            "properties": {
                "ref:De_Lijn": "102701",
                "bus": "yes",
                "name": "Sint-Lenaarts Laboureur",
                "public_transport": "platform",
                "highway": "bus_stop",
                "created_by": "HOOGSTRAATSEBAAN SINT-LENAARTS",
                "operator": "De Lijn",
                "network": "DLAn"
            },
            "geometry": {
                "type": "Point",
                "coordinates": [
                    4.712137,
                    51.370527
                ]
            }
        },
        {
            "type": "Feature",
            "properties": {
                "ref:De_Lijn": "102702",
                "bus": "yes",
                "name": "Sint-Lenaarts Laboureur",
                "public_transport": "platform",
                "highway": "bus_stop",
                "created_by": "HOOGSTRAATSEBAAN SINT-LENAARTS",
                "operator": "De Lijn",
                "network": "DLAn"
            },
            "geometry": {
                "type": "Point",
                "coordinates": [
                    4.712034,
                    51.370221
                ]
            }
        }
    ]
}